drb_client/__init__.py
drb_client/__main__.py
drb_client/asdnotify.py
drb_client/bn256.py
drb_client/crypto.py
drb_client/net.py
drb_client/sink.py
drb_client/utils.py
drb_client-0.4.0.dist-info/LICENSE
drb_client-0.4.0.dist-info/METADATA
drb_client-0.4.0.dist-info/WHEEL
drb_client-0.4.0.dist-info/entry_points.txt
drb_client-0.4.0.dist-info/top_level.txt
drb_client-0.4.0.dist-info/zip-safe
drb_client-0.4.0.dist-info/RECORD
