Metadata-Version: 2.1
Name: drb-client
Version: 0.4.0
Summary: Distributed Randomness Beacon client
Home-page: https://github.com/Snawoot/drb-client
Author: Vladislav Yarmak
Author-email: vladislav-ex-src@vm-0.com
License: MIT
Platform: UNKNOWN
Classifier: Programming Language :: Python :: 3.5
Classifier: License :: OSI Approved :: MIT License
Classifier: Operating System :: POSIX :: Linux
Classifier: Development Status :: 4 - Beta
Classifier: Environment :: No Input/Output (Daemon)
Classifier: Intended Audience :: System Administrators
Classifier: Natural Language :: English
Classifier: Topic :: Internet
Classifier: Topic :: Security
Classifier: Topic :: System :: Operating System Kernels :: Linux
Classifier: Topic :: Security :: Cryptography
Classifier: Topic :: Utilities
Requires-Python: >=3.5.3
Requires-Dist: aiohttp (>=3.4.4)
Requires-Dist: cryptography (>=2.0)
Requires-Dist: toml
Requires-Dist: async-exit-stack
